MANIFEST.in
README.rst
TortoiseSVNPlugin.py
setup.py
robotframework_ride_tortoisesvn.egg-info/PKG-INFO
robotframework_ride_tortoisesvn.egg-info/SOURCES.txt
robotframework_ride_tortoisesvn.egg-info/dependency_links.txt
robotframework_ride_tortoisesvn.egg-info/requires.txt
robotframework_ride_tortoisesvn.egg-info/top_level.txt