Metadata-Version: 1.1
Name: robotframework-ride-tortoisesvn
Version: 0.1.1
Summary: TortoiseSVN plugin for Robotframework IDE (RIDE).
Home-page: https://github.com/ukostas/robotframework-ride-tortoisesvn
Author: ukostas
Author-email: UNKNOWN
License: UNKNOWN
Keywords: robotframework testing testautomation tortoise svn plugin ride
Platform: UNKNOWN
Classifier: Development Status :: 5 - Production/Stable
Classifier: Intended Audience :: Developers
Classifier: Environment :: Plugins
Classifier: Topic :: Software Development :: Testing
Classifier: Programming Language :: Python :: 2
Classifier: Programming Language :: Python :: 3
Classifier: Framework :: Robot Framework
Classifier: Operating System :: Microsoft :: Windows
